semrush/__init__.py
semrush/_logging.py
semrush/cli.py
semrush/resources.py
semrush/commands/__init__.py
semrush/commands/accounts.py
semrush/commands/analytics.py
semrush/commands/projects.py
semrush_cli-1.0.1.dist-info/LICENSE
semrush_cli-1.0.1.dist-info/METADATA
semrush_cli-1.0.1.dist-info/WHEEL
semrush_cli-1.0.1.dist-info/entry_points.txt
semrush_cli-1.0.1.dist-info/top_level.txt
semrush_cli-1.0.1.dist-info/RECORD
